hagstofan/__init__.py
hagstofan/hagstofan.py
hagstofan/configs/table_data.json
hagstofan-0.1.1.dist-info/LICENSE
hagstofan-0.1.1.dist-info/METADATA
hagstofan-0.1.1.dist-info/WHEEL
hagstofan-0.1.1.dist-info/top_level.txt
hagstofan-0.1.1.dist-info/RECORD
