Metadata-Version: 2.1
Name: hagstofan
Version: 0.1.1
Summary: API wrapper fyrir Hagstofuna
Author: Halldór Kristinsson
Author-email: halldor.kristinsson@sedlabanki.is
License: MIT
Project-URL: Source, https://github.com/datador/hagstofan
License-File: LICENSE
Requires-Dist: aiohttp (>=3.7.4)
Requires-Dist: requests (>=2.25.1)
Requires-Dist: pandas (>=1.2.4)
Requires-Dist: nest-asyncio (>=1.5.1)
